bootstrap/__init__.py
bootstrap/apps.py
bootstrap/widgets.py
bootstrap/static/bootstrap/bootstrap-dialog/bootstrap-dialog.css
bootstrap/static/bootstrap/bootstrap-dialog/bootstrap-dialog.js
bootstrap/static/bootstrap/bootstrap-icons/bootstrap-icons.svg
bootstrap/static/bootstrap/bootstrap-icons/font/bootstrap-icons.css
bootstrap/static/bootstrap/bootstrap-icons/font/bootstrap-icons.json
bootstrap/static/bootstrap/bootstrap-icons/font/bootstrap-icons.min.css
bootstrap/static/bootstrap/bootstrap-icons/font/bootstrap-icons.scss
bootstrap/static/bootstrap/bootstrap-icons/font/fonts/bootstrap-icons.woff
bootstrap/static/bootstrap/bootstrap-icons/font/fonts/bootstrap-icons.woff2
bootstrap/static/bootstrap/css/bootstrap-grid.css
bootstrap/static/bootstrap/css/bootstrap-grid.css.map
bootstrap/static/bootstrap/css/bootstrap-grid.min.css
bootstrap/static/bootstrap/css/bootstrap-grid.min.css.map
bootstrap/static/bootstrap/css/bootstrap-grid.rtl.css
bootstrap/static/bootstrap/css/bootstrap-grid.rtl.css.map
bootstrap/static/bootstrap/css/bootstrap-grid.rtl.min.css
bootstrap/static/bootstrap/css/bootstrap-grid.rtl.min.css.map
bootstrap/static/bootstrap/css/bootstrap-reboot.css
bootstrap/static/bootstrap/css/bootstrap-reboot.css.map
bootstrap/static/bootstrap/css/bootstrap-reboot.min.css
bootstrap/static/bootstrap/css/bootstrap-reboot.min.css.map
bootstrap/static/bootstrap/css/bootstrap-reboot.rtl.css
bootstrap/static/bootstrap/css/bootstrap-reboot.rtl.css.map
bootstrap/static/bootstrap/css/bootstrap-reboot.rtl.min.css
bootstrap/static/bootstrap/css/bootstrap-reboot.rtl.min.css.map
bootstrap/static/bootstrap/css/bootstrap-utilities.css
bootstrap/static/bootstrap/css/bootstrap-utilities.css.map
bootstrap/static/bootstrap/css/bootstrap-utilities.min.css
bootstrap/static/bootstrap/css/bootstrap-utilities.min.css.map
bootstrap/static/bootstrap/css/bootstrap-utilities.rtl.css
bootstrap/static/bootstrap/css/bootstrap-utilities.rtl.css.map
ims_bootstrap-5.3.0.dist-info/METADATA
ims_bootstrap-5.3.0.dist-info/WHEEL
ims_bootstrap-5.3.0.dist-info/licenses/LICENSE
ims_bootstrap-5.3.0.dist-info/RECORD
